[{
		"name": 1,
		"problem": "建筑施工企业管理人员安全生产考核合格证书有效期为（ D  ）年，有效期满需要延期的，应当于期满前（ D ）个月内向原发证机关申请办理延期手续。",
		"type": 1,
		"answer": "D",

		"list": [{
				"choise": "A: 1,3"
			},
			{
				"choise": "B: 3,2"
			},
			{
				"choise": "C:3,1"
			},
			{
				"choise": "D:3,3"
			}
		]

	},
	{
		"name": 2,
		"problem": ".施工单位应当在施工组织设计中编制安全技术措施和施工现场临时用电方案，对达到一定规模的危险性较大分部分项工程编制专项施工方案，并附具安全验算结果，经施工单位（   ）、总监理工程师签字后实施。",
		"type": 1,
		"answer": "B",

		"list": [{
				"choise": "A: 企业负责人"
			},
			{
				"choise": "B: 技术负责人"
			},
			{
				"choise": "C: 项目经理"
			},
			{
				"choise": "D：工长"
			}
		]

	}

]
